LICENSE
MANIFEST.in
README.md
setup.py
TonX.egg-info/PKG-INFO
TonX.egg-info/SOURCES.txt
TonX.egg-info/dependency_links.txt
TonX.egg-info/requires.txt
TonX.egg-info/top_level.txt
tonx/__init__.py
tonx/client.py
tonx/generate_files.py
tonx/generate_json.py
tonx/tonlib_api.json
tonx/tonlib_api.tl
tonx/exceptions/__init__.py
tonx/lib/__init__.py
tonx/lib/download_binaries.py
tonx/methods/__init__.py
tonx/methods/tonlib_functions.py
tonx/payments/__init__.py
tonx/payments/payments.py
tonx/tonapi/__init__.py
tonx/tonapi/ton.py
tonx/types/__init__.py
tonx/types/tonlib_types.py
tonx/utils/__init__.py
tonx/utils/_address.py
tonx/utils/_json_encoder.py
tonx/utils/_parse_data.py
tonx/utils/_strings.py
tonx/utils/_value.py