Metadata-Version: 2.1
Name: TonX
Version: 0.1.1
Summary: A user-friendly Python library for interacting with TON (The Open Network), offering convenient payment handling and much more.
Home-page: https://github.com/AYMENJD/tonx
Author: AYMEN Mohammed
Author-email: let.me.code.safe@gmail.com
License: MIT
Project-URL: Source, https://github.com/AYMENJD/tonx
Project-URL: Tracker, https://github.com/AYMENJD/tonx/issues
Keywords: ton,telegram,cryptocurrency,blockchain,tonlib,payments,crypto,digital currency,decentralized,smart contracts,dApp,Ethereum,Bitcoin,cryptocurrency payments,crypto wallet,transaction,secure,privacy,token,block explorer,smart contract development
Platform: UNKNOWN
Requires-Python: >=3.9
Provides-Extra: payments
License-File: LICENSE
